{"concludeQuestions":{"support":"No","confidence":"Moderately confident in my conclusion","improve":"more sampling in other similar locations"},"isAlternativeHypo":true,"form":{"consistent":{"value":"Yes"},"evenly-space":{"value":"Yes"},"consistent-reason":{"value":"5 is enough where outliers can be identified"},"evenly-space-reason":{"value":"easier to compare results; say \"apples to apples\""},"p1-support":{"value":"Yes"},"p1-confidence":{"value":"Moderately confident in this conclusion"},"p2-support":{"value":"Yes"},"p2-confidence":{"value":"Moderately confident in this conclusion"},"p3-support":{"value":"Yes"},"p3-confidence":{"value":"Moderately confident in this conclusion"},"p4-support":{"value":"Yes"},"p4-confidence":{"value":"Moderately confident in this conclusion"},"age":{"value":"30"},"gender":{"value":"female","reason":""},"if-bachelor":{"value":"Yes"},"years-of-practice":{"value":"6"},"geoscientist-or-psychologist":{"value":"Geoscientist","reason":""},"familiarity":{"value":"I am not familiar with any features","reason":""},"academia-or-industry":{"value":"Academia","reason":""},"identification":{"value":"Field Geoscientist","reason":""},"geoscience-specialization":{"value":"sedimentology"},"academia-position":{"value":"Graduate Students"}},"rows":[{"index":0,"measurements":5,"type":"normal","normOffsetX":242.00471192974942,"normOffsetY":71.50139216106233,"roc":"I don’t have enough information to make a confidence judgment"},{"index":1,"measurements":5,"type":"normal","normOffsetX":290.4056543156993,"normOffsetY":73.70143499678733,"roc":"I don’t have enough information to make a confidence judgment"},{"index":2,"measurements":5,"type":"normal","normOffsetX":337.70657528378666,"normOffsetY":80.3015635039623,"roc":"I don’t have enough information to make a confidence judgment"},{"index":4,"measurements":5,"type":"normal","normOffsetX":387.20753908759906,"normOffsetY":90.20175626472478,"roc":"Slightly confident the data supports the hypothesis"},{"index":6,"measurements":5,"type":"normal","normOffsetX":434.50846005568644,"normOffsetY":96.80188477189976,"roc":"Slightly confident the data supports the hypothesis"},{"index":7,"measurements":5,"type":"normal","normOffsetX":478.50931677018633,"normOffsetY":107.80209895052474,"roc":"Slightly confident the data supports the hypothesis"},{"index":8,"measurements":5,"type":"normal","normOffsetX":522.5101734846862,"normOffsetY":121.00235596487471,"roc":"Slightly confident the data supports the hypothesis"},{"index":10,"measurements":5,"type":"normal","normOffsetX":565.4110087813236,"normOffsetY":130.9025487256372,"roc":"Slightly confident the data supports the hypothesis"},{"index":11,"measurements":5,"type":"normal","normOffsetX":609.4118654958235,"normOffsetY":150.70293424716212,"roc":"Slightly confident the data supports the hypothesis"},{"index":13,"measurements":5,"type":"normal","normOffsetX":654.512743628186,"normOffsetY":171.60334118654959,"roc":"Slightly confident the data supports the hypothesis"},{"index":14,"measurements":5,"type":"normal","normOffsetX":697.4135789248234,"normOffsetY":193.60376954379953,"roc":"Moderately confident the data supports the hypothesis"},{"index":15,"measurements":5,"type":"normal","normOffsetX":740.3144142214607,"normOffsetY":216.70421931891198,"roc":"Moderately confident the data supports the hypothesis"},{"index":17,"measurements":5,"type":"normal","normOffsetX":783.4902548725637,"normOffsetY":242.00471192974942,"roc":"Moderately confident the data supports the hypothesis"},{"index":18,"measurements":5,"type":"normal","normOffsetX":827.4911115870636,"normOffsetY":270.6052687941743,"roc":"Moderately confident the data supports the hypothesis"},{"index":19,"measurements":5,"type":"normal","normOffsetX":875.8920539730135,"normOffsetY":291.5056757335618,"roc":"Moderately confident the data supports the hypothesis"},{"index":21,"measurements":5,"type":"normal","normOffsetX":919.8929106875133,"normOffsetY":289.3056328978368,"roc":"Moderately confident the data supports the hypothesis"}]}